Metadata-Version: 2.1
Name: rhasspy-dialogue-hermes
Version: 0.5.0
Summary: UNKNOWN
Home-page: https://github.com/rhasspy/rhasspy-dialogue-hermes
Author: Michael Hansen
Author-email: mike@rhasspy.org
License: UNKNOWN
Platform: UNKNOWN
Classifier: Programming Language :: Python :: 3
Classifier: Programming Language :: Python :: 3.7
Classifier: Programming Language :: Python :: 3.8
Classifier: License :: OSI Approved :: MIT License
Requires-Python: >=3.7
